data_lineage/__init__.py
data_lineage/__main__.py
data_lineage/assets/favicon.ico
data_lineage/graph.py
data_lineage/parser/__init__.py
data_lineage/parser/binder.py
data_lineage/parser/dml_visitor.py
data_lineage/parser/visitor.py
data_lineage/server.py
data_lineage/worker.py
data_lineage-0.9.0.dist-info/entry_points.txt
data_lineage-0.9.0.dist-info/LICENSE
data_lineage-0.9.0.dist-info/WHEEL
data_lineage-0.9.0.dist-info/METADATA
data_lineage-0.9.0.dist-info/RECORD
