Metadata-Version: 2.1
Name: data-lineage
Version: 0.9.0
Summary: Open Source Data Lineage Tool for Redshift. Snowflake and many other databases
Home-page: https://tokern.io/
License: MIT
Keywords: data-lineage,postgres,snowflake,redshift,glue
Author: Tokern
Author-email: info@tokern.io
Requires-Python: >=3.8,<4.0
Classifier: Development Status :: 3 - Alpha
Classifier: Intended Audience :: Developers
Classifier: License :: OSI Approved :: MIT License
Classifier: Programming Language :: Python
Classifier: Programming Language :: Python :: 3
Classifier: Programming Language :: Python :: 3.7
Classifier: Programming Language :: Python :: 3.8
Classifier: Programming Language :: Python :: 3.9
Classifier: Topic :: Database
Classifier: Topic :: Software Development
Classifier: Topic :: Software Development :: Libraries :: Python Modules
Requires-Dist: PyYAML
Requires-Dist: SQLAlchemy (>=1.3,<2.0)
Requires-Dist: botocore (>=1.20,<2.0)
Requires-Dist: click (>=7,<8)
Requires-Dist: dbcat (>=0.7.1,<0.8.0)
Requires-Dist: flask (>=1.1,<2.0)
Requires-Dist: flask-restful
Requires-Dist: flask-restless-ng
Requires-Dist: furl
Requires-Dist: gunicorn
Requires-Dist: inflection
Requires-Dist: networkx
Requires-Dist: pglast
Requires-Dist: psycopg2 (>=2.9.1,<3.0.0)
Requires-Dist: redis (>=3.5.3,<4.0.0)
Requires-Dist: requests
Requires-Dist: rq (>=1.10.0,<2.0.0)
Project-URL: Repository, https://github.com/tokern/data-lineage/
